{
  "_meta": {
    "generated_at": "2026-03-16T04:23:46.308835",
    "target_url": "https://example.com",
    "phase": "recon",
    "version": "1.0.0",
    "run_id": "721d959a-e94d-4443-b0c1-3fe7181091bb"
  },
  "state_diffs": {
    "unverified": {
      "state": "unverified",
      "available_actions": [
        "Learn more"
      ],
      "available_endpoints": [],
      "visible_ui_elements": [
        "Example Domain"
      ],
      "transitions_allowed": []
    },
    "verified": {
      "state": "verified",
      "available_actions": [
        "Learn more"
      ],
      "available_endpoints": [],
      "visible_ui_elements": [
        "Example Domain"
      ],
      "transitions_allowed": []
    },
    "trial": {
      "state": "trial",
      "available_actions": [
        "Learn more"
      ],
      "available_endpoints": [],
      "visible_ui_elements": [
        "Example Domain"
      ],
      "transitions_allowed": []
    },
    "paid": {
      "state": "paid",
      "available_actions": [
        "Learn more"
      ],
      "available_endpoints": [],
      "visible_ui_elements": [
        "Example Domain"
      ],
      "transitions_allowed": []
    },
    "free": {
      "state": "free",
      "available_actions": [
        "Learn more"
      ],
      "available_endpoints": [],
      "visible_ui_elements": [
        "Example Domain"
      ],
      "transitions_allowed": []
    }
  },
  "detected_states": [],
  "states_analyzed": [
    "unverified",
    "verified",
    "trial",
    "paid",
    "free"
  ]
}